scuid/__init__.py
scuid/scuid.py
scuid-0.3.3.dist-info/LICENSE
scuid-0.3.3.dist-info/METADATA
scuid-0.3.3.dist-info/WHEEL
scuid-0.3.3.dist-info/RECORD
