Metadata-Version: 2.1
Name: scuid
Version: 0.3.3
Summary: scuid is a lightweight Python library for generating collision-resistant IDs optimized for horizontal scaling and high performance. It serves as a slim, alternative implementation of cuid with added flexibility for customization, including support for custom random number generators.
Author: Hieu Lam
Author-email: lamhieu.vk@gmail.com
Requires-Python: >=3.10,<4.0
Classifier: Programming Language :: Python :: 3
Classifier: Programming Language :: Python :: 3.10
Classifier: Programming Language :: Python :: 3.11
Classifier: Programming Language :: Python :: 3.12
Classifier: Programming Language :: Python :: 3.13
Requires-Dist: pytest (>=8.3.4,<9.0.0)
